{
    "asset": {
        "format": "jpeg",
        "id": "d0ccb0091eb695f0bddd7177d157d743",
        "name": "mutple%20(15).jpeg",
        "path": "file:C:/Users/ForTa/OneDrive%20-%20%E6%96%87%E6%95%99%E5%A4%A7%E5%AD%A6/2025_One/ProSemD/vott/mutple%20(15).jpeg",
        "size": {
            "width": 500,
            "height": 333
        },
        "state": 2,
        "type": 1
    },
    "regions": [
        {
            "id": "VdbgieP0uZ",
            "type": "RECTANGLE",
            "tags": [
                "basket"
            ],
            "boundingBox": {
                "height": 56.65689568318112,
                "width": 62.98030148964679,
                "left": 363.9175429339708,
                "top": 183.71869102800395
            },
            "points": [
                {
                    "x": 363.9175429339708,
                    "y": 183.71869102800395
                },
                {
                    "x": 426.89784442361764,
                    "y": 183.71869102800395
                },
                {
                    "x": 426.89784442361764,
                    "y": 240.37558671118506
                },
                {
                    "x": 363.9175429339708,
                    "y": 240.37558671118506
                }
            ]
        },
        {
            "id": "-aX14B8slM",
            "type": "RECTANGLE",
            "tags": [
                "basket"
            ],
            "boundingBox": {
                "height": 44.50356535575758,
                "width": 58.200568044531984,
                "left": 126.52296157450797,
                "top": 89.16544872874947
            },
            "points": [
                {
                    "x": 126.52296157450797,
                    "y": 89.16544872874947
                },
                {
                    "x": 184.72352961903994,
                    "y": 89.16544872874947
                },
                {
                    "x": 184.72352961903994,
                    "y": 133.66901408450704
                },
                {
                    "x": 126.52296157450797,
                    "y": 133.66901408450704
                }
            ]
        }
    ],
    "version": "2.2.0"
}