{
    "asset": {
        "format": "jpeg",
        "id": "cc340ae8737c132dcd19482f8de886f3",
        "name": "child%20sheet%20(123).jpeg",
        "path": "file:C:/Users/ForTa/OneDrive%20-%20%E6%96%87%E6%95%99%E5%A4%A7%E5%AD%A6/2025_One/ProSemD/vott/child%20sheet%20(123).jpeg",
        "size": {
            "width": 720,
            "height": 572
        },
        "state": 2,
        "type": 1
    },
    "regions": [
        {
            "id": "q_1oWMQHVH",
            "type": "RECTANGLE",
            "tags": [
                "basket"
            ],
            "boundingBox": {
                "height": 157.51556473161708,
                "width": 207.0090105433664,
                "left": 0,
                "top": 147.16785235381008
            },
            "points": [
                {
                    "x": 0,
                    "y": 147.16785235381008
                },
                {
                    "x": 207.0090105433664,
                    "y": 147.16785235381008
                },
                {
                    "x": 207.0090105433664,
                    "y": 304.68341708542715
                },
                {
                    "x": 0,
                    "y": 304.68341708542715
                }
            ]
        },
        {
            "id": "-vtJaFBHBm",
            "type": "RECTANGLE",
            "tags": [
                "battery"
            ],
            "boundingBox": {
                "height": 92.5547870271769,
                "width": 60.93412296500748,
                "left": 452.4700708446388,
                "top": 263.2924579256144
            },
            "points": [
                {
                    "x": 452.4700708446388,
                    "y": 263.2924579256144
                },
                {
                    "x": 513.4041938096464,
                    "y": 263.2924579256144
                },
                {
                    "x": 513.4041938096464,
                    "y": 355.8472449527913
                },
                {
                    "x": 452.4700708446388,
                    "y": 355.8472449527913
                }
            ]
        },
        {
            "id": "_319gBxZZb",
            "type": "RECTANGLE",
            "tags": [
                "childseat"
            ],
            "boundingBox": {
                "height": 258.1186017367109,
                "width": 181.652685839259,
                "left": 525.476041325552,
                "top": 86.23115577889448
            },
            "points": [
                {
                    "x": 525.476041325552,
                    "y": 86.23115577889448
                },
                {
                    "x": 707.128727164811,
                    "y": 86.23115577889448
                },
                {
                    "x": 707.128727164811,
                    "y": 344.34975751560535
                },
                {
                    "x": 525.476041325552,
                    "y": 344.34975751560535
                }
            ]
        }
    ],
    "version": "2.2.0"
}